ai_idea_cli-0.3.0.dist-info/licenses/LICENSE
idea/__init__.py
idea/cli.py
idea/config.py
idea/demo.py
idea/issue_reporter.py
idea/llm.py
idea/models.py
idea/py.typed
idea/queue.py
idea/router.py
idea/validator.py
idea/clients/__init__.py
idea/clients/base.py
idea/clients/experience.py
idea/clients/planner.py
idea/clients/queue.py
idea/scaffold/__init__.py
idea/scaffold/node.py
idea/scaffold/python.py
ai_idea_cli-0.3.0.dist-info/METADATA
ai_idea_cli-0.3.0.dist-info/WHEEL
ai_idea_cli-0.3.0.dist-info/entry_points.txt
ai_idea_cli-0.3.0.dist-info/top_level.txt
ai_idea_cli-0.3.0.dist-info/RECORD
