Metadata-Version: 2.4
Name: ai-idea-cli
Version: 0.3.0
Summary: AI-powered project scaffolding CLI with demo mode for immediate usage
Author-email: idea-cli <noreply@idea-cli.com>
License-Expression: MIT
Project-URL: Homepage, https://github.com/oxygen-fragment/ai-idea-cli
Project-URL: Repository, https://github.com/oxygen-fragment/ai-idea-cli
Project-URL: Documentation, https://github.com/oxygen-fragment/ai-idea-cli/blob/main/README.md
Project-URL: Bug Tracker, https://github.com/oxygen-fragment/ai-idea-cli/issues
Keywords: ai,scaffolding,cli,project-generator,sdlc
Classifier: Development Status :: 4 - Beta
Classifier: Intended Audience :: Developers
Classifier: Programming Language :: Python :: 3
Classifier: Programming Language :: Python :: 3.12
Classifier: Topic :: Software Development :: Code Generators
Classifier: Topic :: Software Development :: Libraries :: Application Frameworks
Requires-Python: >=3.12
License-File: LICENSE
Requires-Dist: typer[all]>=0.12.0
Requires-Dist: rich>=13.0.0
Requires-Dist: pydantic>=2.0.0
Requires-Dist: jsonschema>=4.0.0
Requires-Dist: python-dotenv>=1.0.0
Requires-Dist: httpx>=0.27.0
Requires-Dist: copier>=9.0.0
Provides-Extra: dev
Requires-Dist: pytest>=8.0.0; extra == "dev"
Requires-Dist: pytest-cov>=5.0.0; extra == "dev"
Requires-Dist: black>=24.0.0; extra == "dev"
Requires-Dist: ruff>=0.4.0; extra == "dev"
Requires-Dist: mypy>=1.10.0; extra == "dev"
Requires-Dist: pre-commit>=3.7.0; extra == "dev"
Provides-Extra: llm
Requires-Dist: anthropic>=0.34.0; extra == "llm"
Requires-Dist: openai>=1.0.0; extra == "llm"
Dynamic: license-file
